{
  "update_timestamp": "2025-06-28 06:31:06",
  "cities_header": "Detaliczne ceny paliw w poszczególnych miastach wojewódzkich w dniu 2025-06-25",
  "cities": {
    "Białystok": {
      "prices": {
        "PB95": 5.914,
        "PB98": 6.632,
        "ON": 6.0333,
        "LPG": 2.771
      }
    },
    "Bydgoszcz": {
      "prices": {
        "PB95": 6.0119,
        "PB98": 6.812,
        "ON": 6.1427,
        "LPG": 2.773
      }
    },
    "Gdańsk": {
      "prices": {
        "PB95": 5.8623,
        "PB98": 6.542,
        "ON": 5.9028,
        "LPG": 2.744
      }
    },
    "Gorzów Wlkp.": {
      "prices": {
        "PB95": 5.9826,
        "PB98": 6.7122,
        "ON": 6.003,
        "LPG": 2.992
      }
    },
    "Katowice": {
      "prices": {
        "PB95": 5.9325,
        "PB98": 6.812,
        "ON": 6.044,
        "LPG": 2.67
      }
    },
    "Kielce": {
      "prices": {
        "PB95": 6.1222,
        "PB98": 6.8914,
        "ON": 6.213,
        "LPG": 2.691
      }
    },
    "Kraków": {
      "prices": {
        "PB95": 5.8523,
        "PB98": 6.4717,
        "ON": 5.9029,
        "LPG": 2.581
      }
    },
    "Lublin": {
      "prices": {
        "PB95": 5.9114,
        "PB98": 6.6719,
        "ON": 6.0027,
        "LPG": 2.701
      }
    },
    "Łódź": {
      "prices": {
        "PB95": 5.872,
        "PB98": 6.6218,
        "ON": 5.983,
        "LPG": 2.661
      }
    },
    "Olsztyn": {
      "prices": {
        "PB95": 5.9219,
        "PB98": 6.6731,
        "ON": 6.0337,
        "LPG": 2.702
      }
    },
    "Opole": {
      "prices": {
        "PB95": 6.042,
        "PB98": 6.872,
        "ON": 6.1331,
        "LPG": 2.761
      }
    },
    "Poznań": {
      "prices": {
        "PB95": 5.8517,
        "PB98": 6.5513,
        "ON": 6.0133,
        "LPG": 2.689
      }
    },
    "Rzeszów": {
      "prices": {
        "PB95": 5.9922,
        "PB98": 6.7014,
        "ON": 6.0325,
        "LPG": 2.761
      }
    },
    "Szczecin": {
      "prices": {
        "PB95": 5.8921,
        "PB98": 6.6921,
        "ON": 5.9529,
        "LPG": 2.988
      }
    },
    "Warszawa": {
      "prices": {
        "PB95": 6.0819,
        "PB98": 6.7514,
        "ON": 6.1733,
        "LPG": 2.851
      }
    },
    "Wrocław": {
      "prices": {
        "PB95": 5.8724,
        "PB98": 6.5918,
        "ON": 6.0929,
        "LPG": 2.812
      }
    }
  }
}